s3_bucket/__init__.py
s3_bucket/bucket.py
s3_bucket/exceptions.py
s3_bucket-1.4.0.dist-info/LICENSE
s3_bucket-1.4.0.dist-info/METADATA
s3_bucket-1.4.0.dist-info/WHEEL
s3_bucket-1.4.0.dist-info/top_level.txt
s3_bucket-1.4.0.dist-info/RECORD
