Metadata-Version: 2.1
Name: s3-bucket
Version: 1.4.0
Summary: An easy to use client for S3
Home-page: https://github.com/CodeLighthouse/s3-bucket
Author: CodeLighthouse
Author-email: hello@codelighthouse.io
License: MIT
Platform: UNKNOWN
Requires-Python: >=3.6
Requires-Dist: boto3
